getSecrets/__init__.py
get_hc_secrets-1.5.23.dist-info/licenses/LICENSE
get_hc_secrets-1.5.23.dist-info/METADATA
get_hc_secrets-1.5.23.dist-info/WHEEL
get_hc_secrets-1.5.23.dist-info/top_level.txt
get_hc_secrets-1.5.23.dist-info/RECORD
