Metadata-Version: 2.4
Name: get_hc_secrets
Version: 1.5.23
Summary: A package to read secrets from Hashicorp vault or from a local file
Author-email: Xavier Mayeur <xavier@mayeur.be>
Project-URL: Homepage, https://github.com/xmayeur/getSecrets
Project-URL: Bug Tracker, https://github.com/xmayeur/getSecrets/issues
Classifier: Programming Language :: Python :: 3
Classifier: License :: OSI Approved :: MIT License
Classifier: Operating System :: OS Independent
Requires-Python: >=3.7
License-File: LICENSE
Requires-Dist: pyyaml
Requires-Dist: requests
Dynamic: license-file
